charonload/__init__.py
charonload/_config.py
charonload/_errors.py
charonload/_finder.py
charonload/_persistence.py
charonload/_runner.py
charonload/_version.py
charonload/py.typed
charonload/_compat/__init__.py
charonload/_compat/hashlib.py
charonload/_compat/tomllib.py
charonload/_compat/typing.py
charonload/cmake/charonload-config-version.cmake
charonload/cmake/charonload-config.cmake
charonload/cmake/detect_configure_failure.cmake
charonload/cmake/prefix_paths.cmake
charonload/cmake/torch/add_torch_library.cmake
charonload/cmake/torch/cuda_version.cmake
charonload/cmake/torch/cxx11_abi.cmake
charonload/cmake/torch/cxx_standard.cmake
charonload/cmake/torch/torch_extension_name.cmake
charonload/cmake/torch/cxx_standard/CMakeLists.txt
charonload/cmake/torch/cxx_standard/torch_cxx_standard.cpp
charonload/pybind11_stubgen/__init__.py
charonload/pybind11_stubgen/__main__.py
charonload-0.2.1.dist-info/licenses/LICENSE
charonload-0.2.1.dist-info/METADATA
charonload-0.2.1.dist-info/WHEEL
charonload-0.2.1.dist-info/top_level.txt
charonload-0.2.1.dist-info/RECORD
