Metadata-Version: 2.4
Name: charonload
Version: 0.2.1
Summary: Develop C++/CUDA extensions with PyTorch like Python scripts
Author-email: Patrick Stotko <stotko@cs.uni-bonn.de>
Project-URL: Homepage, https://github.com/vc-bonn/charonload
Project-URL: Repository, https://github.com/vc-bonn/charonload
Project-URL: Documentation, https://vc-bonn.github.io/charonload/
Project-URL: Changelog, https://github.com/vc-bonn/charonload/blob/main/CHANGELOG.md
Classifier: Development Status :: 4 - Beta
Classifier: License :: OSI Approved :: MIT License
Classifier: Programming Language :: C++
Classifier: Programming Language :: Python :: 3 :: Only
Classifier: Programming Language :: Python :: 3.9
Classifier: Programming Language :: Python :: 3.10
Classifier: Programming Language :: Python :: 3.11
Classifier: Programming Language :: Python :: 3.12
Classifier: Programming Language :: Python :: 3.13
Classifier: Topic :: Scientific/Engineering
Classifier: Topic :: Software Development :: Libraries :: Python Modules
Classifier: Intended Audience :: Developers
Classifier: Intended Audience :: Science/Research
Requires-Python: >=3.9
License-File: LICENSE
Requires-Dist: cmake>=3.27
Requires-Dist: ninja; platform_system != "Windows"
Requires-Dist: filelock
Requires-Dist: torch
Requires-Dist: numpy
Requires-Dist: colorama>=0.4.6
Requires-Dist: pybind11-stubgen>=2.3
Requires-Dist: tomli; python_version < "3.11"
Requires-Dist: typing-extensions; python_version < "3.11"
Provides-Extra: dev
Requires-Dist: build; extra == "dev"
Requires-Dist: black~=25.0; extra == "dev"
Requires-Dist: isort; extra == "dev"
Requires-Dist: docformatter; extra == "dev"
Requires-Dist: clang-format~=14.0; extra == "dev"
Requires-Dist: ruff>=0.6; extra == "dev"
Requires-Dist: mypy; extra == "dev"
Requires-Dist: codespell; extra == "dev"
Requires-Dist: check-manifest; extra == "dev"
Requires-Dist: sphinx; extra == "dev"
Requires-Dist: furo; extra == "dev"
Requires-Dist: sphinx-autobuild; extra == "dev"
Requires-Dist: sphinx-autodoc-typehints>=2.0; extra == "dev"
Requires-Dist: sphinx_autodoc_defaultargs; extra == "dev"
Requires-Dist: sphinx_copybutton; extra == "dev"
Requires-Dist: sphinx_design; extra == "dev"
Requires-Dist: sphinxcontrib-moderncmakedomain; extra == "dev"
Requires-Dist: myst-parser; extra == "dev"
Requires-Dist: docutils>=0.17; extra == "dev"
Requires-Dist: pytest; extra == "dev"
Requires-Dist: pytest-datadir; extra == "dev"
Requires-Dist: pytest-cov; extra == "dev"
Requires-Dist: pytest-mock; extra == "dev"
Requires-Dist: nox; extra == "dev"
Dynamic: license-file
